{
  "_fv": 57,
  "_type": "loottable",
  "definition": {
    "type": "Fishing",
    "pools": [
      {
        "minrolls": 1,
        "maxrolls": 1,
        "minbonusrolls": 1,
        "maxbonusrolls": 1,
        "hasbonusrolls": false,
        "entries": [
          {
            "type": "item",
            "item": {
              "value": "Blocks.WATERLILY"
            },
            "weight": 17,
            "minCount": 1,
            "maxCount": 1,
            "minEnchantmentLevel": 0,
            "maxEnchantmentLevel": 0,
            "affectedByFortune": false,
            "explosionDecay": false,
            "silkTouchMode": 0
          },
          {
            "type": "item",
            "item": {
              "value": "Items.BOWL"
            },
            "weight": 10,
            "minCount": 1,
            "maxCount": 1,
            "minEnchantmentLevel": 0,
            "maxEnchantmentLevel": 0,
            "affectedByFortune": false,
            "explosionDecay": false,
            "silkTouchMode": 0
          },
          {
            "type": "item",
            "item": {
              "value": "Items.FISHING_ROD"
            },
            "weight": 2,
            "minCount": 1,
            "maxCount": 1,
            "minEnchantmentLevel": 0,
            "maxEnchantmentLevel": 0,
            "affectedByFortune": false,
            "explosionDecay": false,
            "silkTouchMode": 0
          },
          {
            "type": "item",
            "item": {
              "value": "Items.LEATHER"
            },
            "weight": 10,
            "minCount": 1,
            "maxCount": 1,
            "minEnchantmentLevel": 0,
            "maxEnchantmentLevel": 0,
            "affectedByFortune": false,
            "explosionDecay": false,
            "silkTouchMode": 0
          },
          {
            "type": "item",
            "item": {
              "value": "Items.LEATHER_BOOTS"
            },
            "weight": 10,
            "minCount": 1,
            "maxCount": 1,
            "minEnchantmentLevel": 0,
            "maxEnchantmentLevel": 0,
            "affectedByFortune": false,
            "explosionDecay": false,
            "silkTouchMode": 0
          },
          {
            "type": "item",
            "item": {
              "value": "Items.ROTTEN_FLESH"
            },
            "weight": 10,
            "minCount": 1,
            "maxCount": 1,
            "minEnchantmentLevel": 0,
            "maxEnchantmentLevel": 0,
            "affectedByFortune": false,
            "explosionDecay": false,
            "silkTouchMode": 0
          },
          {
            "type": "item",
            "item": {
              "value": "Blocks.BAMBOO"
            },
            "weight": 5,
            "minCount": 1,
            "maxCount": 1,
            "minEnchantmentLevel": 0,
            "maxEnchantmentLevel": 0,
            "affectedByFortune": false,
            "explosionDecay": false,
            "silkTouchMode": 0
          },
          {
            "type": "item",
            "item": {
              "value": "Items.STRING"
            },
            "weight": 5,
            "minCount": 1,
            "maxCount": 1,
            "minEnchantmentLevel": 0,
            "maxEnchantmentLevel": 0,
            "affectedByFortune": false,
            "explosionDecay": false,
            "silkTouchMode": 0
          },
          {
            "type": "item",
            "item": {
              "value": "Items.POTIONITEM"
            },
            "weight": 10,
            "minCount": 1,
            "maxCount": 1,
            "minEnchantmentLevel": 0,
            "maxEnchantmentLevel": 0,
            "affectedByFortune": false,
            "explosionDecay": false,
            "silkTouchMode": 0
          },
          {
            "type": "item",
            "item": {
              "value": "Items.BONE"
            },
            "weight": 10,
            "minCount": 1,
            "maxCount": 1,
            "minEnchantmentLevel": 0,
            "maxEnchantmentLevel": 0,
            "affectedByFortune": false,
            "explosionDecay": false,
            "silkTouchMode": 0
          },
          {
            "type": "item",
            "item": {
              "value": "Items.DYE#0"
            },
            "weight": 1,
            "minCount": 10,
            "maxCount": 10,
            "minEnchantmentLevel": 0,
            "maxEnchantmentLevel": 0,
            "affectedByFortune": false,
            "explosionDecay": false,
            "silkTouchMode": 0
          }
        ]
      }
    ],
    "name": "gameplay/fishing/junk",
    "namespace": "minecraft"
  }
}